llama_cloud_services/__init__.py
llama_cloud_services/constants.py
llama_cloud_services/utils.py
llama_cloud_services/beta/agent_data/__init__.py
llama_cloud_services/beta/agent_data/client.py
llama_cloud_services/beta/agent_data/schema.py
llama_cloud_services/beta/classifier/__init__.py
llama_cloud_services/beta/classifier/client.py
llama_cloud_services/beta/classifier/types.py
llama_cloud_services/beta/sheets/__init__.py
llama_cloud_services/beta/sheets/client.py
llama_cloud_services/beta/sheets/types.py
llama_cloud_services/extract/__init__.py
llama_cloud_services/extract/extract.py
llama_cloud_services/extract/utils.py
llama_cloud_services/files/__init__.py
llama_cloud_services/files/client.py
llama_cloud_services/index/__init__.py
llama_cloud_services/index/api_utils.py
llama_cloud_services/index/base.py
llama_cloud_services/index/composite_retriever.py
llama_cloud_services/index/retriever.py
llama_cloud_services/parse/__init__.py
llama_cloud_services/parse/base.py
llama_cloud_services/parse/types.py
llama_cloud_services/parse/utils.py
llama_cloud_services/parse/cli/__init__.py
llama_cloud_services/parse/cli/main.py
llama_cloud_services-0.6.87.dist-info/METADATA
llama_cloud_services-0.6.87.dist-info/WHEEL
llama_cloud_services-0.6.87.dist-info/entry_points.txt
llama_cloud_services-0.6.87.dist-info/licenses/LICENSE
llama_cloud_services-0.6.87.dist-info/RECORD
