Metadata-Version: 2.4
Name: llama-cloud-services
Version: 0.6.87
Summary: Tailored SDK clients for LlamaCloud services.
Author-email: Logan Markewich <logan@runllama.ai>
License-Expression: MIT
License-File: LICENSE
Requires-Python: <4.0,>=3.9
Requires-Dist: click<9,>=8.1.7
Requires-Dist: eval-type-backport<0.3,>=0.2.0; python_version < '3.10'
Requires-Dist: llama-cloud==0.1.45
Requires-Dist: llama-index-core>=0.12.0
Requires-Dist: packaging>=23.0
Requires-Dist: platformdirs<5,>=4.3.7
Requires-Dist: pydantic!=2.10,>=2.8
Requires-Dist: python-dotenv<2,>=1.0.1
Requires-Dist: tenacity<10.0,>=8.5.0
